benchmark/__init__.py
benchmark/__init__.pyc
benchmark/layout_comparison.pyc
benchmark/test_scbench.py
benchmark/benchmark_scbench/__init__.py
benchmark/benchmark_scbench/__init__.pyc
benchmark/benchmark_scbench/batch.pyc
benchmark/benchmark_scbench/constants.pyc
benchmark/benchmark_scbench/evaluator.pyc
benchmark/benchmark_scbench/promptor.pyc
benchmark/benchmark_scbench/utils.pyc
benchmark/benchmark_scbench/vllm_direct_generator.pyc
benchmark/benchmark_scbench/multi_turn/__init__.py
benchmark/benchmark_scbench/multi_turn/__init__.pyc
benchmark/benchmark_scbench/multi_turn/config/__init__.py
benchmark/benchmark_scbench/multi_turn/config/__init__.pyc
benchmark/benchmark_scbench/multi_turn/pipelines/__init__.py
benchmark/benchmark_scbench/multi_turn/pipelines/__init__.pyc
benchmark/benchmark_scbench/multi_turn/pipelines/baseline_multi_turn.pyc
benchmark/benchmark_scbench/multi_turn/pipelines/ehpc_multi_turn.pyc
benchmark/benchmark_scbench/multi_turn/pipelines/llmlingua2_multi_turn.pyc
benchmark/benchmark_scbench/multi_turn/pipelines/longllmlingua_multi_turn.pyc
benchmark/benchmark_scbench/multi_turn/pipelines/longrefiner_multi_turn.pyc
benchmark/benchmark_scbench/multi_turn/pipelines/provence_multi_turn.pyc
benchmark/benchmark_scbench/multi_turn/pipelines/recomp_abst_multi_turn.pyc
benchmark/benchmark_scbench/multi_turn/pipelines/recomp_extr_multi_turn.pyc
benchmark/benchmark_scbench/scdq/__init__.py
benchmark/benchmark_scbench/scdq/__init__.pyc
benchmark/benchmark_scbench/scdq/config/__init__.py
benchmark/benchmark_scbench/scdq/config/__init__.pyc
benchmark/benchmark_scbench/scdq/pipelines/__init__.py
benchmark/benchmark_scbench/scdq/pipelines/__init__.pyc
benchmark/benchmark_scbench/scdq/pipelines/baseline_scdq.pyc
sagellm_kv_cache/__init__.py
sagellm_kv_cache/__init__.pyc
sagellm_kv_cache/distributed.pyc
sagellm_kv_cache/errors.pyc
sagellm_kv_cache/transfer.pyc
sagellm_kv_cache/__pycache__/__init__.cpython-311.pyc
sagellm_kv_cache/layout/__init__.py
isagellm_kv_cache-0.4.0.7.dist-info/METADATA
isagellm_kv_cache-0.4.0.7.dist-info/WHEEL
isagellm_kv_cache-0.4.0.7.dist-info/top_level.txt
isagellm_kv_cache-0.4.0.7.dist-info/RECORD
