Metadata-Version: 2.4
Name: isagellm-kv-cache
Version: 0.4.0.7
Summary: KV Cache Management Module for sageLLM
Author-email: IntelliStream Team <shuhao_zhang@hust.edu.cn>
License: Private
Project-URL: Homepage, https://github.com/intellistream/sagellm-kv-cache
Project-URL: Repository, https://github.com/intellistream/sagellm-kv-cache
Project-URL: Issues, https://github.com/intellistream/sagellm-kv-cache/issues
Keywords: llm,inference,kv-cache,domestic-hardware
Classifier: Development Status :: 3 - Alpha
Classifier: Intended Audience :: Developers
Classifier: Programming Language :: Python :: 3.10
Classifier: Programming Language :: Python :: 3.11
Requires-Python: ==3.11.*
Requires-Dist: pydantic>=2.0.0
Requires-Dist: isagellm-protocol<0.5.0,>=0.4.0.0
Requires-Dist: isagellm-backend<0.5.0,>=0.4.0.0
Requires-Dist: isagellm-comm<0.5.0,>=0.4.0.0
Provides-Extra: dev
Requires-Dist: pytest>=7.0.0; extra == "dev"
Requires-Dist: pytest-cov>=4.0.0; extra == "dev"
Requires-Dist: mypy>=1.0.0; extra == "dev"
Requires-Dist: ruff>=0.1.0; extra == "dev"
Requires-Dist: isage-pypi-publisher>=0.2.0; extra == "dev"
